mt_UI/__init__.py
mt_UI/mt_UI.py
mt_UI-0.0.2.dist-info/LICENSE
mt_UI-0.0.2.dist-info/METADATA
mt_UI-0.0.2.dist-info/WHEEL
mt_UI-0.0.2.dist-info/top_level.txt
mt_UI-0.0.2.dist-info/RECORD
